linnian/apps/chatter/__init__.py
linnian/apps/chatter/chat_types.py
linnian/apps/chatter/test.py
linnian/apps/chatter/utils.py
linnian_apps_chatter-0.2.0.dist-info/LICENSE
linnian_apps_chatter-0.2.0.dist-info/WHEEL
linnian_apps_chatter-0.2.0.dist-info/METADATA
linnian_apps_chatter-0.2.0.dist-info/RECORD
