Metadata-Version: 2.1
Name: linnian-apps-chatter
Version: 0.2.0
Summary: qwq
License: MIT
Author: LinNian
Author-email: 2544704967@qq.com
Requires-Python: >=3.8,<4.0
Classifier: License :: OSI Approved :: MIT License
Classifier: Programming Language :: Python :: 3
Classifier: Programming Language :: Python :: 3.8
Classifier: Programming Language :: Python :: 3.9
Requires-Dist: aiofiles (>=0.4.0,<0.5.0)
Requires-Dist: loguru (>=0.4.0,<0.5.0)
Requires-Dist: pydantic (>=1.6.1,<2.0.0)
Requires-Dist: ujson (>=4.0.2,<5.0.0)
